ark_metrics_collector/__init__.py
ark_metrics_collector/app.py
ark_metrics_collector/config.py
ark_metrics_collector/log_parser.py
ark_metrics_collector/main.py
ark_metrics_collector/metrics.py
ark_metrics_collector/polling.py
ark_metrics_collector-0.2.0.dist-info/METADATA
ark_metrics_collector-0.2.0.dist-info/WHEEL
ark_metrics_collector-0.2.0.dist-info/entry_points.txt
ark_metrics_collector-0.2.0.dist-info/top_level.txt
ark_metrics_collector-0.2.0.dist-info/RECORD
