Metadata-Version: 2.1
Name: ark_metrics_collector
Version: 0.2.0
Requires-Dist: Flask
Requires-Dist: prometheus-client
Requires-Dist: pyyaml
